setup.py
odoo/addons/export_contract_data_form_view/CHANGELOG.md
odoo/addons/export_contract_data_form_view/README.rst
odoo/addons/export_contract_data_form_view/__init__.py
odoo/addons/export_contract_data_form_view/__manifest__.py
odoo/addons/export_contract_data_form_view/static/src/js/contract_form_controller.js
odoo/addons/export_contract_data_form_view/static/src/js/contract_form_view.js
odoo/addons/export_contract_data_form_view/views/contract_views.xml
odoo_addon_export_contract_data_form_view.egg-info/PKG-INFO
odoo_addon_export_contract_data_form_view.egg-info/SOURCES.txt
odoo_addon_export_contract_data_form_view.egg-info/dependency_links.txt
odoo_addon_export_contract_data_form_view.egg-info/not-zip-safe
odoo_addon_export_contract_data_form_view.egg-info/requires.txt
odoo_addon_export_contract_data_form_view.egg-info/top_level.txt